LICENCE.txt
README.md
setup.py
src/MPT5/Allimp.py
src/MPT5/Mainpro.py
src/MPT5/__init__.py
src/MPT5/__main__.py
src/MPT5/make.py
src/MPT5/update.py
src/MPT5.0.1.2.egg-info/PKG-INFO
src/MPT5.0.1.2.egg-info/SOURCES.txt
src/MPT5.0.1.2.egg-info/dependency_links.txt
src/MPT5.0.1.2.egg-info/requires.txt
src/MPT5.0.1.2.egg-info/top_level.txt
src/MPT5/AI/Analiz.py
src/MPT5/AI/DBgen.py
src/MPT5/AI/Generats.py
src/MPT5/AI/OpnSrc.py
src/MPT5/AI/__init__.py
src/MPT5/AI/DL/__init__.py
src/MPT5/AI/ML/__init__.py
src/MPT5/AI/Test/AppTest.py
src/MPT5/AI/Test/__init__.py
src/MPT5/Config/Init.py
src/MPT5/Config/__init__.py
src/MPT5/DCC1/AuiPan2.py
src/MPT5/DCC1/DBDev2.py
src/MPT5/DCC1/ListPro2.py
src/MPT5/DCC1/MLDev2.py
src/MPT5/DCC1/MenuDev2.py
src/MPT5/DCC1/ProgDev2.py
src/MPT5/DCC1/Proper2.py
src/MPT5/DCC1/ToolBar2.py
src/MPT5/DCC1/__init__.py
src/MPT5/Database/MenuSet2.py
src/MPT5/Database/PostGet.py
src/MPT5/Database/PostGet2.py
src/MPT5/Database/__init__.py
src/MPT5/Database/dbinterface.py
src/MPT5/Database/srcsql.py
src/MPT5/Database/wxsq.py
src/MPT5/Database/sqls/__init__.py
src/MPT5/Fount/Allimp.py
src/MPT5/Fount/Mainpro.py
src/MPT5/Fount/__init__.py
src/MPT5/Fount/update.py
src/MPT5/GUI/BG2.py
src/MPT5/GUI/MainMenu2.py
src/MPT5/GUI/MainTool.py
src/MPT5/GUI/Start.py
src/MPT5/GUI/__init__.py
src/MPT5/GUI/proman.py
src/MPT5/GUI/window2.py
src/MPT5/GUI/API/SamPnl.py
src/MPT5/GUI/API/__init__.py
src/MPT5/GUI/AuiPanel/PAui.py
src/MPT5/GUI/AuiPanel/__init__.py
src/MPT5/GUI/AuiPanel/tempane.py
src/MPT5/GUI/Main/DBv1.py
src/MPT5/GUI/Main/MDv1.py
src/MPT5/GUI/Main/MLv1.py
src/MPT5/GUI/Main/PAv1.py
src/MPT5/GUI/Main/PGv1.py
src/MPT5/GUI/Main/PPv1.py
src/MPT5/GUI/Main/TBv1.py
src/MPT5/GUI/Main/TPv1.py
src/MPT5/GUI/Main/__init__.py
src/MPT5/GUI/Temp/Demo.py
src/MPT5/GUI/Temp/Muntitle.py
src/MPT5/GUI/Temp/__init__.py
src/MPT5/GUI/Temp/untitle.py
src/MPT5/Locale/__init__.py
src/MPT5/Logs/__init__.py
src/MPT5/Res/Allicons.py
src/MPT5/Res/__init__.py
src/MPT5/Res/Fonts/__init__.py
src/MPT5/Res/Icons/__init__.py
src/MPT5/Res/Icons/16x16/__init__.py
src/MPT5/Res/Icons/32x32/__init__.py
src/MPT5/Res/Icons/Menu/__init__.py
src/MPT5/Res/Icons/Toolbar/__init__.py
