Metadata-Version: 2.1
Name: MPT5.0.1.2
Version: 0.1.2
Summary: MPT5 Test ML Environment
Home-page: https://github.com/Srcfount/MPT5/
Author: Pooya Ghiami
Author-email: pooyagheyami@gmail.com
License: GNU
Keywords: MACHINELEARNING GUI SQL
License-File: LICENCE.txt
